cs1/__init__.py
cs1/cs.py
cs1/metrics.py
cs1/basis/__init__.py
cs1/basis/common.py
cs1/basis/adaptive/__init__.py
cs1/basis/adaptive/vae.py
cs1/domain/__init__.py
cs1/domain/audio.py
cs1/domain/image.py
cs1/gui/__init__.py
cs1/gui/run.py
cs1/gui/static/__init__.py
cs1/gui/static/bootstrap-dialog.css
cs1/gui/static/bootstrap.css
cs1/gui/static/bootstrap.js
cs1/gui/static/font-awesome.css
cs1/gui/static/jquery-3.3.1.min.js
cs1/gui/static/jquery-ui-1.12.1.js
cs1/gui/static/jquery-ui.css
cs1/gui/static/jquery.blockUI.js
cs1/gui/static/jquery.form.min.js
cs1/gui/static/seedrandom.js
cs1/gui/static/utility.chart.js
cs1/gui/static/fonts/FontAwesome.otf
cs1/gui/static/fonts/__init__.py
cs1/gui/static/fonts/fontawesome-webfont.eot
cs1/gui/static/fonts/fontawesome-webfont.svg
cs1/gui/static/fonts/fontawesome-webfont.ttf
cs1/gui/static/fonts/fontawesome-webfont.woff
cs1/gui/static/fonts/fontawesome-webfont.woff2
cs1/gui/static/fonts/glyphicons-halflings-regular.eot
cs1/gui/static/fonts/glyphicons-halflings-regular.svg
cs1/gui/static/fonts/glyphicons-halflings-regular.ttf
cs1/gui/static/fonts/glyphicons-halflings-regular.woff
cs1/gui/static/fonts/glyphicons-halflings-regular.woff2
cs1/gui/static/images/BCoT.png
cs1/gui/static/images/DCT.png
cs1/gui/static/images/DFT.png
cs1/gui/static/images/DFT_A.png
cs1/gui/static/images/DFT_P.png
cs1/gui/static/images/HWT.png
cs1/gui/static/images/IDM.png
cs1/gui/static/images/SECS.png
cs1/gui/static/images/Sensing - clean.png
cs1/gui/static/images/__init__.py
cs1/gui/static/images/reconstruction - clean.png
cs1/gui/static/images/reconstruction.png
cs1/gui/static/images/sensing matrix - clean.png
cs1/gui/static/images/sensing matrix.jpeg
cs1/gui/static/images/sensing.png
cs1/gui/templates/__init__.py
cs1/gui/templates/home.html
cs1/gui/templates/receiver.html
cs1/gui/templates/tutorial.html
cs1/security/__init__.py
cs1/security/tvsm.py
cs1-0.2.7.dist-info/LICENCE
cs1-0.2.7.dist-info/METADATA
cs1-0.2.7.dist-info/WHEEL
cs1-0.2.7.dist-info/top_level.txt
cs1-0.2.7.dist-info/RECORD
