Metadata-Version: 2.1
Name: cs1
Version: 0.2.7
Summary: Compressed Sensing library for 1D Spectroscopic Profiling Data
Home-page: https://github.com/zhangys11/cs1
Author: Yinsheng Zhang (Ph.D.)
Author-email: oo@zju.edu.cn
Project-URL: Bug Tracker, https://github.com/zhangys11/cs1/issues
Classifier: Programming Language :: Python :: 3
Classifier: License :: OSI Approved :: GNU Lesser General Public License v3 or later (LGPLv3+)
Classifier: Operating System :: OS Independent
Classifier: Topic :: Scientific/Engineering :: Mathematics
Requires-Python: >=3.6
License-File: LICENCE
Requires-Dist: scikit-learn
Requires-Dist: matplotlib
Requires-Dist: numpy
Requires-Dist: PyWavelets
Requires-Dist: statsmodels
Requires-Dist: pydub
Requires-Dist: opencv-python
Requires-Dist: torch
Requires-Dist: torchvision
Requires-Dist: torchviz
Requires-Dist: scipy
